{"context":{"domain":"nic2004:52110","country":"IND","city":"std:080","core_version":"1.0.0","action":"status","bap_id":"beta.mystore.in","bap_uri":"https:\/\/beta.mystore.in\/ondc\/1.0\/","bpp_id":"retailconnect.co.in","bpp_uri":"https:\/\/retailconnect.co.in\/ondc\/public\/OndcPreProd\/callback","transaction_id":"3d36fe5a-f659-4fff-8b34-af355af9171c","message_id":"077a023f-6233-4b93-9d7a-69bd3cc99c7b","timestamp":"2022-09-22T14:14:48.662Z","ttl":"PT30S"},"message":{"order_id":"632c6dc33fbf937abd66a68a"}} null